libgraphite
