Metadata-Version: 1.1
Name: libgraphite
Version: 0.1.3dev
Summary: Graphite querying library
Home-page: https://github.com/direvius/libgraphite
Author: Alexey Lavrenuke (load testing)
Author-email: direvius@yandex-team.ru
License: LGPLv3
Platform: UNKNOWN
Classifier: Topic :: Software Development :: Libraries
Classifier: Topic :: Scientific/Engineering :: Information Analysis
